django_bigbluebutton/__init__.py
django_bigbluebutton/admin.py
django_bigbluebutton/apps.py
django_bigbluebutton/bbb.py
django_bigbluebutton/forms.py
django_bigbluebutton/models.py
django_bigbluebutton/settings.py
django_bigbluebutton/signals.py
django_bigbluebutton/tasks.py
django_bigbluebutton/tests.py
django_bigbluebutton/urls.py
django_bigbluebutton/utils.py
django_bigbluebutton/api/__init__.py
django_bigbluebutton/api/serializers.py
django_bigbluebutton/api/urls.py
django_bigbluebutton/api/views.py
django_bigbluebutton/api/__pycache__/__init__.cpython-36.pyc
django_bigbluebutton/api/__pycache__/serializers.cpython-36.pyc
django_bigbluebutton/api/__pycache__/urls.cpython-36.pyc
django_bigbluebutton/api/__pycache__/views.cpython-36.pyc
django_bigbluebutton/locale/fa/LC_MESSAGES/django.mo
django_bigbluebutton/locale/fa/LC_MESSAGES/django.po
django_bigbluebutton/migrations/0001_initial.py
django_bigbluebutton/migrations/0002_auto_20200831_1635.py
django_bigbluebutton/migrations/0003_auto_20200831_1644.py
django_bigbluebutton/migrations/0004_meeting_is_running.py
django_bigbluebutton/migrations/0005_auto_20200911_0547.py
django_bigbluebutton/migrations/0006_auto_20200911_0622.py
django_bigbluebutton/migrations/0007_auto_20200925_0959.py
django_bigbluebutton/migrations/0008_auto_20201008_1609.py
django_bigbluebutton/migrations/0009_auto_20201112_1032.py
django_bigbluebutton/migrations/0010_auto_20201126_0923.py
django_bigbluebutton/migrations/0011_meetinglog.py
django_bigbluebutton/migrations/0012_meetinglog_meeting.py
django_bigbluebutton/migrations/0013_auto_20201211_0601.py
django_bigbluebutton/migrations/0014_auto_20201211_0920.py
django_bigbluebutton/migrations/0015_auto_20201214_1423.py
django_bigbluebutton/migrations/0016_auto_20210202_1546.py
django_bigbluebutton/migrations/0017_auto_20210202_1600.py
django_bigbluebutton/migrations/__init__.py
django_bigbluebutton/templates/admin/meeting_create_link.html
django_bigbluebutton-0.5.8.dist-info/LICENSE
django_bigbluebutton-0.5.8.dist-info/METADATA
django_bigbluebutton-0.5.8.dist-info/WHEEL
django_bigbluebutton-0.5.8.dist-info/top_level.txt
django_bigbluebutton-0.5.8.dist-info/RECORD
