Metadata-Version: 2.1
Name: django-bigbluebutton
Version: 0.5.8
Summary: A Django integration APP to connect django projects to Big Blue Button ;)
Home-page: https://github.com/Execut3/django-bigbluebutton
Author: Execut3
Author-email: execut3.binarycodes@gmail.com
License: GPT
Platform: UNKNOWN
Requires-Dist: Django (>=2.0)
Requires-Dist: requests (>=2.0)
Requires-Dist: djangorestframework (>=3.0.0)
